nc4_tools/__init__.py
nc4_tools/_logging.py
nc4_tools/duplicate_var.py
nc4_tools/ncdataset.py
nc4_tools/nctemplate.py
nc4_tools/ncvarslice.py
nc4_tools/py.typed
nc4_tools-1.1.2.dist-info/METADATA
nc4_tools-1.1.2.dist-info/WHEEL
nc4_tools-1.1.2.dist-info/licenses/LICENSE
nc4_tools-1.1.2.dist-info/RECORD
