Metadata-Version: 2.4
Name: nc4-tools
Version: 1.1.2
Summary: Tools to aid some tasks of working with the netcdf4-python library
Project-URL: Repository, https://gitlab.com/osu-nrsg/nc4-tools
Author-email: Randall Pittman <randall.pittman@oregonstate.edu>
License: MIT License
License-File: LICENSE
Keywords: dataset,netcdf,netcdf4,template
Classifier: Development Status :: 4 - Beta
Classifier: Intended Audience :: Developers
Classifier: License :: OSI Approved :: MIT License
Classifier: Programming Language :: Python :: 3
Classifier: Topic :: Scientific/Engineering
Requires-Python: >=3.9
Requires-Dist: netcdf4~=1.7.2
